xl_pq_handler/__init__.py
xl_pq_handler/handler.py
xl_pq_handler/py.typed
xl_pq_handler-1.0.4.dist-info/WHEEL
xl_pq_handler-1.0.4.dist-info/METADATA
xl_pq_handler-1.0.4.dist-info/RECORD
