Metadata-Version: 2.4
Name: xl-pq-handler
Version: 1.0.4
Summary: A Pythonic Power Query (.pq) File Manager for Excel & Power BI Automation
Keywords: Power Query,Excel,Power BI,Automation,Analytics,Audit
Author: tks18
Author-email: tks18 <tksudharshan@gmail.com>
License-Expression: GPL-3.0-only
Classifier: Development Status :: 5 - Production/Stable
Classifier: Intended Audience :: Developers
Classifier: Intended Audience :: Financial and Insurance Industry
Classifier: Intended Audience :: Information Technology
Classifier: Topic :: Office/Business :: Financial :: Spreadsheet
Classifier: Topic :: Software Development :: Libraries :: Python Modules
Classifier: Topic :: Utilities
Classifier: License :: OSI Approved :: GNU General Public License v3 (GPLv3)
Classifier: Programming Language :: Python :: 3
Classifier: Programming Language :: Python :: 3.10
Classifier: Programming Language :: Python :: 3.11
Classifier: Programming Language :: Python :: 3.12
Classifier: Programming Language :: Python :: 3.13
Classifier: Operating System :: Microsoft :: Windows
Classifier: Operating System :: MacOS
Classifier: Natural Language :: English
Requires-Dist: pandas>=2.3.3
Requires-Dist: pyperclip>=1.11.0
Requires-Dist: pyyaml>=6.0.3
Requires-Dist: xlwings>=0.33.16
Requires-Python: >=3.13
Project-URL: Changelog, https://github.com/tks18/xl-pq-handler/releases
Project-URL: Documentation, https://github.com/tks18/xl-pq-handler#readme
Project-URL: Homepage, https://github.com/tks18/xl-pq-handler
Project-URL: Issues, https://github.com/tks18/xl-pq-handler/issues
Project-URL: Repository, https://github.com/tks18/xl-pq-handler
